implements_helper/__init__.py
implements_helper/utility_methods.py
implements_helper-1.0.7.dist-info/LICENSE
implements_helper-1.0.7.dist-info/METADATA
implements_helper-1.0.7.dist-info/WHEEL
implements_helper-1.0.7.dist-info/top_level.txt
implements_helper-1.0.7.dist-info/RECORD
