Metadata-Version: 2.2
Name: implements-helper
Version: 1.0.7
Summary: Python実装時に利用できるユーティリティ群
Author: Mikimini9627
Project-URL: Homepage, https://github.com/Mikimini9627/implements_helper
Project-URL: Repository, https://github.com/Mikimini9627/implements_helper
Classifier: Intended Audience :: Developers
Classifier: License :: OSI Approved :: MIT License
Classifier: Programming Language :: Python :: 3.12
Requires-Python: >=3.12
License-File: LICENSE
